simple_acme_dns/__init__.py
simple_acme_dns/errors.py
simple_acme_dns/tools.py
simple_acme_dns-4.0.0.dist-info/licenses/LICENSE
simple_acme_dns-4.0.0.dist-info/METADATA
simple_acme_dns-4.0.0.dist-info/WHEEL
simple_acme_dns-4.0.0.dist-info/top_level.txt
simple_acme_dns-4.0.0.dist-info/RECORD
