Metadata-Version: 2.4
Name: simple_acme_dns
Version: 4.0.0
Summary: A Python ACME client for the DNS-01 challenge
Home-page: https://github.com/jaredhendrickson13/simple_acme_dns
Author: Jared Hendrickson
Author-email: github@jaredhendrickson.com
License: Apache-2.0
Classifier: Programming Language :: Python :: 3
Classifier: License :: OSI Approved :: Apache Software License
Classifier: Operating System :: OS Independent
Requires-Python: >=3.9
License-File: LICENSE
Requires-Dist: acme~=4.1.1
Requires-Dist: validators~=0.35.0
Requires-Dist: dnspython~=2.7.0
Dynamic: author
Dynamic: author-email
Dynamic: classifier
Dynamic: description
Dynamic: description-content-type
Dynamic: home-page
Dynamic: license
Dynamic: license-file
Dynamic: requires-dist
Dynamic: requires-python
Dynamic: summary
